{
  "peak_predicted_mllw": 5.622,
  "peak_forecast_observed_mllw": 5.622,
  "peak_time_local": "2026-05-20 23:57",
  "current_surge_ft": -0.1215,
  "peak_rain_rate_in_hr": 0.0,
  "temp_avg_72h_f": 75.18191933240614,
  "cold_lockout": false,
  "depths_in": {
    "lowest_sentinel_grate": 0.0,
    "lowest_road_corner": 0.0,
    "gutter_walkway": 0.0,
    "corner_grate": 0.0,
    "curb": 0.0,
    "road_middle": 0.0,
    "intersection": 0.0,
    "lawn_step": 0.0,
    "porch_step": 0.0,
    "regime": "dry"
  },
  "surge_source": "surge-persistence",
  "nws_status": "not active",
  "all_tides": [
    {
      "time": "2026-05-20 23:57",
      "predicted_mllw": 5.622,
      "surge_ft": -0.1215,
      "forecast_peak_mllw": 5.622,
      "peak_rain_in_hr": 0.0,
      "peak_rain_offset_h": null,
      "rain_window_3h": [],
      "source": "surge-persistence",
      "depths_in": {
        "lowest_sentinel_grate": 0.0,
        "lowest_road_corner": 0.0,
        "gutter_walkway": 0.0,
        "corner_grate": 0.0,
        "curb": 0.0,
        "road_middle": 0.0,
        "intersection": 0.0,
        "lawn_step": 0.0,
        "porch_step": 0.0,
        "regime": "dry"
      },
      "hours_from_now": 2.084739788333333
    },
    {
      "time": "2026-05-21 12:45",
      "predicted_mllw": 4.8,
      "surge_ft": -0.1215,
      "forecast_peak_mllw": 4.8,
      "peak_rain_in_hr": 0.0,
      "peak_rain_offset_h": null,
      "rain_window_3h": [],
      "source": "surge-persistence",
      "depths_in": {
        "lowest_sentinel_grate": 0.0,
        "lowest_road_corner": 0.0,
        "gutter_walkway": 0.0,
        "corner_grate": 0.0,
        "curb": 0.0,
        "road_middle": 0.0,
        "intersection": 0.0,
        "lawn_step": 0.0,
        "porch_step": 0.0,
        "regime": "dry"
      },
      "hours_from_now": 14.884739773333333
    },
    {
      "time": "2026-05-22 00:58",
      "predicted_mllw": 5.329,
      "surge_ft": -0.1215,
      "forecast_peak_mllw": 5.329,
      "peak_rain_in_hr": 0.0,
      "peak_rain_offset_h": null,
      "rain_window_3h": [],
      "source": "surge-persistence",
      "depths_in": {
        "lowest_sentinel_grate": 0.0,
        "lowest_road_corner": 0.0,
        "gutter_walkway": 0.0,
        "corner_grate": 0.0,
        "curb": 0.0,
        "road_middle": 0.0,
        "intersection": 0.0,
        "lawn_step": 0.0,
        "porch_step": 0.0,
        "regime": "dry"
      },
      "hours_from_now": 27.101406428333334
    },
    {
      "time": "2026-05-22 13:44",
      "predicted_mllw": 4.819,
      "surge_ft": -0.1215,
      "forecast_peak_mllw": 4.819,
      "peak_rain_in_hr": 0.0,
      "peak_rain_offset_h": null,
      "rain_window_3h": [],
      "source": "surge-persistence",
      "depths_in": {
        "lowest_sentinel_grate": 0.0,
        "lowest_road_corner": 0.0,
        "gutter_walkway": 0.0,
        "corner_grate": 0.0,
        "curb": 0.0,
        "road_middle": 0.0,
        "intersection": 0.0,
        "lawn_step": 0.0,
        "porch_step": 0.0,
        "regime": "dry"
      },
      "hours_from_now": 39.868073083333336
    },
    {
      "time": "2026-05-23 01:55",
      "predicted_mllw": 5.059,
      "surge_ft": -0.1215,
      "forecast_peak_mllw": 5.059,
      "peak_rain_in_hr": 0.0,
      "peak_rain_offset_h": null,
      "rain_window_3h": [],
      "source": "surge-persistence",
      "depths_in": {
        "lowest_sentinel_grate": 0.0,
        "lowest_road_corner": 0.0,
        "gutter_walkway": 0.0,
        "corner_grate": 0.0,
        "curb": 0.0,
        "road_middle": 0.0,
        "intersection": 0.0,
        "lawn_step": 0.0,
        "porch_step": 0.0,
        "regime": "dry"
      },
      "hours_from_now": 52.051406405555554
    },
    {
      "time": "2026-05-23 14:39",
      "predicted_mllw": 4.865,
      "surge_ft": -0.1215,
      "forecast_peak_mllw": 4.865,
      "peak_rain_in_hr": 0.0,
      "peak_rain_offset_h": null,
      "rain_window_3h": [],
      "source": "surge-persistence",
      "depths_in": {
        "lowest_sentinel_grate": 0.0,
        "lowest_road_corner": 0.0,
        "gutter_walkway": 0.0,
        "corner_grate": 0.0,
        "curb": 0.0,
        "road_middle": 0.0,
        "intersection": 0.0,
        "lawn_step": 0.0,
        "porch_step": 0.0,
        "regime": "dry"
      },
      "hours_from_now": 64.78473972083333
    }
  ],
  "low_tides": [
    {
      "time": "2026-05-21 06:31",
      "value_mllw": -0.1
    },
    {
      "time": "2026-05-21 18:36",
      "value_mllw": 0.519
    },
    {
      "time": "2026-05-22 07:31",
      "value_mllw": 0.113
    },
    {
      "time": "2026-05-22 19:43",
      "value_mllw": 0.772
    },
    {
      "time": "2026-05-23 08:32",
      "value_mllw": 0.257
    },
    {
      "time": "2026-05-23 20:52",
      "value_mllw": 0.889
    }
  ],
  "seasonal_context": {
    "month_name": "May",
    "strata": [
      {
        "landmark_key": "lowest_sentinel_grate",
        "landmark_label": "Lowest storm grate (Central Ave)",
        "threshold_ft": 6.02,
        "avg_events": 8.9,
        "avg_days": 8.033333333333333,
        "avg_hours": 18.733333333333334,
        "descriptor": "above-average",
        "window": "1996-2025 (30 yrs)"
      },
      {
        "landmark_key": "lowest_road_corner",
        "landmark_label": "Lowest road corner across Bay",
        "threshold_ft": 6.06,
        "avg_events": 8.5,
        "avg_days": 7.666666666666667,
        "avg_hours": 17.4,
        "descriptor": "above-average",
        "window": "1996-2025 (30 yrs)"
      },
      {
        "landmark_key": "gutter_walkway",
        "landmark_label": "Gutter / curb edge at walkway",
        "threshold_ft": 6.2,
        "avg_events": 6.0,
        "avg_days": 5.433333333333334,
        "avg_hours": 12.4,
        "descriptor": "below-average",
        "window": "1996-2025 (30 yrs)"
      },
      {
        "landmark_key": "corner_grate",
        "landmark_label": "Storm grate at Bay+Central",
        "threshold_ft": 6.33,
        "avg_events": 4.433333333333334,
        "avg_days": 4.166666666666667,
        "avg_hours": 9.166666666666666,
        "descriptor": "below-average",
        "window": "1996-2025 (30 yrs)"
      },
      {
        "landmark_key": "curb",
        "landmark_label": "Curb at walkway",
        "threshold_ft": 6.58,
        "avg_events": 2.6333333333333333,
        "avg_days": 2.5,
        "avg_hours": 5.066666666666666,
        "descriptor": "below-average",
        "window": "1996-2025 (30 yrs)"
      },
      {
        "landmark_key": "road_middle",
        "landmark_label": "Bay Ave road middle",
        "threshold_ft": 6.78,
        "avg_events": 1.6333333333333333,
        "avg_days": 1.5666666666666667,
        "avg_hours": 2.8666666666666667,
        "descriptor": "below-average",
        "window": "1996-2025 (30 yrs)"
      },
      {
        "landmark_key": "intersection",
        "landmark_label": "Intersection center",
        "threshold_ft": 6.96,
        "avg_events": 1.0333333333333334,
        "avg_days": 0.9666666666666667,
        "avg_hours": 1.6333333333333333,
        "descriptor": "above-average",
        "window": "1996-2025 (30 yrs)"
      },
      {
        "landmark_key": "lawn_step",
        "landmark_label": "Lawn / walkway step",
        "threshold_ft": 7.0,
        "avg_events": 0.9,
        "avg_days": 0.8666666666666667,
        "avg_hours": 1.3333333333333333,
        "descriptor": "above-average",
        "window": "1996-2025 (30 yrs)"
      },
      {
        "landmark_key": "porch_step",
        "landmark_label": "Front porch first step",
        "threshold_ft": 7.5,
        "avg_events": 0.16666666666666666,
        "avg_days": 0.16666666666666666,
        "avg_hours": 0.23333333333333334,
        "descriptor": "below-average",
        "window": "1996-2025 (30 yrs)"
      }
    ],
    "mtd": {
      "peak_obs_mllw": 6.546199999999999,
      "peak_6min_mllw": 6.59,
      "peak_6min_time": "2026-05-15 19:24",
      "minutes_above_curb": 18,
      "month_start": "2026-05-01",
      "as_of": "2026-05-20 21:51 UTC",
      "strata": [
        {
          "threshold_ft": 6.02,
          "n_events": 6,
          "n_flood_days": 6,
          "n_hours_above": 11
        },
        {
          "threshold_ft": 6.06,
          "n_events": 6,
          "n_flood_days": 6,
          "n_hours_above": 10
        },
        {
          "threshold_ft": 6.2,
          "n_events": 5,
          "n_flood_days": 5,
          "n_hours_above": 9
        },
        {
          "threshold_ft": 6.33,
          "n_events": 4,
          "n_flood_days": 4,
          "n_hours_above": 5
        },
        {
          "threshold_ft": 6.58,
          "n_events": 0,
          "n_flood_days": 0,
          "n_hours_above": 0
        },
        {
          "threshold_ft": 6.78,
          "n_events": 0,
          "n_flood_days": 0,
          "n_hours_above": 0
        },
        {
          "threshold_ft": 6.96,
          "n_events": 0,
          "n_flood_days": 0,
          "n_hours_above": 0
        },
        {
          "threshold_ft": 7.0,
          "n_events": 0,
          "n_flood_days": 0,
          "n_hours_above": 0
        },
        {
          "threshold_ft": 7.5,
          "n_events": 0,
          "n_flood_days": 0,
          "n_hours_above": 0
        }
      ]
    },
    "slr_ft_since_1990": 0.7860048618417959,
    "slr_reference_year": 1990,
    "show_slr_line": false,
    "slr_today_peak_ft": 5.622
  },
  "cumulative_rain_24h_in": 0.0,
  "surge_swing_6h_ft": 0.9400000000000002,
  "recent_history_7d": [
    {
      "date": "2026-05-13",
      "peak_time": "2026-05-13 21:54",
      "peak_mllw": 2.105,
      "rel_in": -46.980000000000004,
      "highest_landmark": "dry"
    },
    {
      "date": "2026-05-14",
      "peak_time": "2026-05-14 18:30",
      "peak_mllw": 6.275,
      "rel_in": 3.0600000000000094,
      "highest_landmark": "Gutter +0.9\""
    },
    {
      "date": "2026-05-15",
      "peak_time": "2026-05-15 19:24",
      "peak_mllw": 6.59,
      "rel_in": 6.839999999999998,
      "highest_landmark": "Curb +0.1\""
    },
    {
      "date": "2026-05-16",
      "peak_time": "2026-05-16 20:00",
      "peak_mllw": 6.456,
      "rel_in": 5.232000000000015,
      "highest_landmark": "Storm grate +1.5\""
    },
    {
      "date": "2026-05-17",
      "peak_time": "2026-05-17 21:12",
      "peak_mllw": 6.495,
      "rel_in": 5.700000000000012,
      "highest_landmark": "Storm grate +2.0\""
    },
    {
      "date": "2026-05-18",
      "peak_time": "2026-05-18 22:12",
      "peak_mllw": 6.577,
      "rel_in": 6.683999999999999,
      "highest_landmark": "Storm grate +3.0\""
    },
    {
      "date": "2026-05-19",
      "peak_time": "2026-05-19 23:00",
      "peak_mllw": 5.99,
      "rel_in": -0.3599999999999923,
      "highest_landmark": "dry"
    },
    {
      "date": "2026-05-20",
      "peak_time": "2026-05-20 00:00",
      "peak_mllw": 5.488,
      "rel_in": -6.38399999999999,
      "highest_landmark": "dry"
    }
  ],
  "lookahead_watch": [
    {
      "time": "2026-06-13 19:05",
      "time_dt": "2026-06-13 19:05:00",
      "mllw": 6.236,
      "threshold_mllw": 6.2,
      "label": "would reach gutter (no surge needed)",
      "severity_class": "watch-light",
      "spring_tide": "new moon"
    },
    {
      "time": "2026-06-14 19:58",
      "time_dt": "2026-06-14 19:58:00",
      "mllw": 6.386,
      "threshold_mllw": 6.2,
      "label": "would reach gutter (no surge needed)",
      "severity_class": "watch-light",
      "spring_tide": "new moon"
    },
    {
      "time": "2026-06-15 20:51",
      "time_dt": "2026-06-15 20:51:00",
      "mllw": 6.381,
      "threshold_mllw": 6.2,
      "label": "would reach gutter (no surge needed)",
      "severity_class": "watch-light",
      "spring_tide": "new moon"
    },
    {
      "time": "2026-06-16 21:46",
      "time_dt": "2026-06-16 21:46:00",
      "mllw": 6.234,
      "threshold_mllw": 6.2,
      "label": "would reach gutter (no surge needed)",
      "severity_class": "watch-light",
      "spring_tide": "new moon"
    }
  ],
  "live_gauge_24h": [
    {
      "time": "2026-05-19 21:54",
      "value_mllw": 5.668
    },
    {
      "time": "2026-05-19 22:00",
      "value_mllw": 5.704
    },
    {
      "time": "2026-05-19 22:06",
      "value_mllw": 5.731
    },
    {
      "time": "2026-05-19 22:12",
      "value_mllw": 5.777
    },
    {
      "time": "2026-05-19 22:18",
      "value_mllw": 5.826
    },
    {
      "time": "2026-05-19 22:24",
      "value_mllw": 5.852
    },
    {
      "time": "2026-05-19 22:30",
      "value_mllw": 5.901
    },
    {
      "time": "2026-05-19 22:36",
      "value_mllw": 5.921
    },
    {
      "time": "2026-05-19 22:42",
      "value_mllw": 5.934
    },
    {
      "time": "2026-05-19 22:48",
      "value_mllw": 5.973
    },
    {
      "time": "2026-05-19 22:54",
      "value_mllw": 5.977
    },
    {
      "time": "2026-05-19 23:00",
      "value_mllw": 5.99
    },
    {
      "time": "2026-05-19 23:06",
      "value_mllw": 5.983
    },
    {
      "time": "2026-05-19 23:12",
      "value_mllw": 5.977
    },
    {
      "time": "2026-05-19 23:18",
      "value_mllw": 5.957
    },
    {
      "time": "2026-05-19 23:24",
      "value_mllw": 5.918
    },
    {
      "time": "2026-05-19 23:30",
      "value_mllw": 5.878
    },
    {
      "time": "2026-05-19 23:36",
      "value_mllw": 5.829
    },
    {
      "time": "2026-05-19 23:42",
      "value_mllw": 5.757
    },
    {
      "time": "2026-05-19 23:48",
      "value_mllw": 5.675
    },
    {
      "time": "2026-05-19 23:54",
      "value_mllw": 5.583
    },
    {
      "time": "2026-05-20 00:00",
      "value_mllw": 5.488
    },
    {
      "time": "2026-05-20 00:06",
      "value_mllw": 5.386
    },
    {
      "time": "2026-05-20 00:12",
      "value_mllw": 5.307
    },
    {
      "time": "2026-05-20 00:18",
      "value_mllw": 5.202
    },
    {
      "time": "2026-05-20 00:24",
      "value_mllw": 5.071
    },
    {
      "time": "2026-05-20 00:30",
      "value_mllw": 4.983
    },
    {
      "time": "2026-05-20 00:36",
      "value_mllw": 4.878
    },
    {
      "time": "2026-05-20 00:42",
      "value_mllw": 4.76
    },
    {
      "time": "2026-05-20 00:48",
      "value_mllw": 4.628
    },
    {
      "time": "2026-05-20 00:54",
      "value_mllw": 4.533
    },
    {
      "time": "2026-05-20 01:00",
      "value_mllw": 4.395
    },
    {
      "time": "2026-05-20 01:06",
      "value_mllw": 4.248
    },
    {
      "time": "2026-05-20 01:12",
      "value_mllw": 4.12
    },
    {
      "time": "2026-05-20 01:18",
      "value_mllw": 3.982
    },
    {
      "time": "2026-05-20 01:24",
      "value_mllw": 3.824
    },
    {
      "time": "2026-05-20 01:30",
      "value_mllw": 3.67
    },
    {
      "time": "2026-05-20 01:36",
      "value_mllw": 3.529
    },
    {
      "time": "2026-05-20 01:42",
      "value_mllw": 3.395
    },
    {
      "time": "2026-05-20 01:48",
      "value_mllw": 3.247
    },
    {
      "time": "2026-05-20 01:54",
      "value_mllw": 3.113
    },
    {
      "time": "2026-05-20 02:00",
      "value_mllw": 2.991
    },
    {
      "time": "2026-05-20 02:06",
      "value_mllw": 2.86
    },
    {
      "time": "2026-05-20 02:12",
      "value_mllw": 2.745
    },
    {
      "time": "2026-05-20 02:18",
      "value_mllw": 2.584
    },
    {
      "time": "2026-05-20 02:24",
      "value_mllw": 2.47
    },
    {
      "time": "2026-05-20 02:30",
      "value_mllw": 2.355
    },
    {
      "time": "2026-05-20 02:36",
      "value_mllw": 2.217
    },
    {
      "time": "2026-05-20 02:42",
      "value_mllw": 2.086
    },
    {
      "time": "2026-05-20 02:48",
      "value_mllw": 1.971
    },
    {
      "time": "2026-05-20 02:54",
      "value_mllw": 1.853
    },
    {
      "time": "2026-05-20 03:00",
      "value_mllw": 1.741
    },
    {
      "time": "2026-05-20 03:06",
      "value_mllw": 1.63
    },
    {
      "time": "2026-05-20 03:12",
      "value_mllw": 1.518
    },
    {
      "time": "2026-05-20 03:18",
      "value_mllw": 1.4
    },
    {
      "time": "2026-05-20 03:24",
      "value_mllw": 1.292
    },
    {
      "time": "2026-05-20 03:30",
      "value_mllw": 1.19
    },
    {
      "time": "2026-05-20 03:36",
      "value_mllw": 1.092
    },
    {
      "time": "2026-05-20 03:42",
      "value_mllw": 0.964
    },
    {
      "time": "2026-05-20 03:48",
      "value_mllw": 0.862
    },
    {
      "time": "2026-05-20 03:54",
      "value_mllw": 0.76
    },
    {
      "time": "2026-05-20 04:00",
      "value_mllw": 0.662
    },
    {
      "time": "2026-05-20 04:06",
      "value_mllw": 0.586
    },
    {
      "time": "2026-05-20 04:12",
      "value_mllw": 0.465
    },
    {
      "time": "2026-05-20 04:18",
      "value_mllw": 0.383
    },
    {
      "time": "2026-05-20 04:24",
      "value_mllw": 0.298
    },
    {
      "time": "2026-05-20 04:30",
      "value_mllw": 0.222
    },
    {
      "time": "2026-05-20 04:36",
      "value_mllw": 0.147
    },
    {
      "time": "2026-05-20 04:42",
      "value_mllw": 0.071
    },
    {
      "time": "2026-05-20 04:48",
      "value_mllw": -0.017
    },
    {
      "time": "2026-05-20 04:54",
      "value_mllw": -0.06
    },
    {
      "time": "2026-05-20 05:00",
      "value_mllw": -0.135
    },
    {
      "time": "2026-05-20 05:06",
      "value_mllw": -0.191
    },
    {
      "time": "2026-05-20 05:12",
      "value_mllw": -0.217
    },
    {
      "time": "2026-05-20 05:18",
      "value_mllw": -0.237
    },
    {
      "time": "2026-05-20 05:24",
      "value_mllw": -0.26
    },
    {
      "time": "2026-05-20 05:30",
      "value_mllw": -0.29
    },
    {
      "time": "2026-05-20 05:36",
      "value_mllw": -0.273
    },
    {
      "time": "2026-05-20 05:42",
      "value_mllw": -0.273
    },
    {
      "time": "2026-05-20 05:48",
      "value_mllw": -0.26
    },
    {
      "time": "2026-05-20 05:54",
      "value_mllw": -0.25
    },
    {
      "time": "2026-05-20 06:00",
      "value_mllw": -0.224
    },
    {
      "time": "2026-05-20 06:06",
      "value_mllw": -0.175
    },
    {
      "time": "2026-05-20 06:12",
      "value_mllw": -0.142
    },
    {
      "time": "2026-05-20 06:18",
      "value_mllw": -0.083
    },
    {
      "time": "2026-05-20 06:24",
      "value_mllw": -0.011
    },
    {
      "time": "2026-05-20 06:30",
      "value_mllw": 0.071
    },
    {
      "time": "2026-05-20 06:36",
      "value_mllw": 0.16
    },
    {
      "time": "2026-05-20 06:42",
      "value_mllw": 0.248
    },
    {
      "time": "2026-05-20 06:48",
      "value_mllw": 0.353
    },
    {
      "time": "2026-05-20 06:54",
      "value_mllw": 0.455
    },
    {
      "time": "2026-05-20 07:00",
      "value_mllw": 0.573
    },
    {
      "time": "2026-05-20 07:06",
      "value_mllw": 0.675
    },
    {
      "time": "2026-05-20 07:12",
      "value_mllw": 0.783
    },
    {
      "time": "2026-05-20 07:18",
      "value_mllw": 0.911
    },
    {
      "time": "2026-05-20 07:24",
      "value_mllw": 1.026
    },
    {
      "time": "2026-05-20 07:30",
      "value_mllw": 1.118
    },
    {
      "time": "2026-05-20 07:36",
      "value_mllw": 1.229
    },
    {
      "time": "2026-05-20 07:42",
      "value_mllw": 1.341
    },
    {
      "time": "2026-05-20 07:48",
      "value_mllw": 1.475
    },
    {
      "time": "2026-05-20 07:54",
      "value_mllw": 1.6
    },
    {
      "time": "2026-05-20 08:00",
      "value_mllw": 1.735
    },
    {
      "time": "2026-05-20 08:06",
      "value_mllw": 1.853
    },
    {
      "time": "2026-05-20 08:12",
      "value_mllw": 2.01
    },
    {
      "time": "2026-05-20 08:18",
      "value_mllw": 2.128
    },
    {
      "time": "2026-05-20 08:24",
      "value_mllw": 2.256
    },
    {
      "time": "2026-05-20 08:30",
      "value_mllw": 2.391
    },
    {
      "time": "2026-05-20 08:36",
      "value_mllw": 2.502
    },
    {
      "time": "2026-05-20 08:42",
      "value_mllw": 2.65
    },
    {
      "time": "2026-05-20 08:48",
      "value_mllw": 2.791
    },
    {
      "time": "2026-05-20 08:54",
      "value_mllw": 2.903
    },
    {
      "time": "2026-05-20 09:00",
      "value_mllw": 3.021
    },
    {
      "time": "2026-05-20 09:06",
      "value_mllw": 3.155
    },
    {
      "time": "2026-05-20 09:12",
      "value_mllw": 3.277
    },
    {
      "time": "2026-05-20 09:18",
      "value_mllw": 3.391
    },
    {
      "time": "2026-05-20 09:24",
      "value_mllw": 3.506
    },
    {
      "time": "2026-05-20 09:30",
      "value_mllw": 3.628
    },
    {
      "time": "2026-05-20 09:36",
      "value_mllw": 3.739
    },
    {
      "time": "2026-05-20 09:42",
      "value_mllw": 3.844
    },
    {
      "time": "2026-05-20 09:48",
      "value_mllw": 3.956
    },
    {
      "time": "2026-05-20 09:54",
      "value_mllw": 4.077
    },
    {
      "time": "2026-05-20 10:00",
      "value_mllw": 4.172
    },
    {
      "time": "2026-05-20 10:06",
      "value_mllw": 4.271
    },
    {
      "time": "2026-05-20 10:12",
      "value_mllw": 4.392
    },
    {
      "time": "2026-05-20 10:18",
      "value_mllw": 4.461
    },
    {
      "time": "2026-05-20 10:24",
      "value_mllw": 4.55
    },
    {
      "time": "2026-05-20 10:30",
      "value_mllw": 4.622
    },
    {
      "time": "2026-05-20 10:36",
      "value_mllw": 4.723
    },
    {
      "time": "2026-05-20 10:42",
      "value_mllw": 4.763
    },
    {
      "time": "2026-05-20 10:48",
      "value_mllw": 4.848
    },
    {
      "time": "2026-05-20 10:54",
      "value_mllw": 4.904
    },
    {
      "time": "2026-05-20 11:00",
      "value_mllw": 4.97
    },
    {
      "time": "2026-05-20 11:06",
      "value_mllw": 5.019
    },
    {
      "time": "2026-05-20 11:12",
      "value_mllw": 5.052
    },
    {
      "time": "2026-05-20 11:18",
      "value_mllw": 5.058
    },
    {
      "time": "2026-05-20 11:24",
      "value_mllw": 5.117
    },
    {
      "time": "2026-05-20 11:30",
      "value_mllw": 5.101
    },
    {
      "time": "2026-05-20 11:36",
      "value_mllw": 5.084
    },
    {
      "time": "2026-05-20 11:42",
      "value_mllw": 5.088
    },
    {
      "time": "2026-05-20 11:48",
      "value_mllw": 5.065
    },
    {
      "time": "2026-05-20 11:54",
      "value_mllw": 5.029
    },
    {
      "time": "2026-05-20 12:00",
      "value_mllw": 5.009
    },
    {
      "time": "2026-05-20 12:06",
      "value_mllw": 4.97
    },
    {
      "time": "2026-05-20 12:12",
      "value_mllw": 4.91
    },
    {
      "time": "2026-05-20 12:18",
      "value_mllw": 4.858
    },
    {
      "time": "2026-05-20 12:24",
      "value_mllw": 4.779
    },
    {
      "time": "2026-05-20 12:30",
      "value_mllw": 4.717
    },
    {
      "time": "2026-05-20 12:36",
      "value_mllw": 4.622
    },
    {
      "time": "2026-05-20 12:42",
      "value_mllw": 4.523
    },
    {
      "time": "2026-05-20 12:48",
      "value_mllw": 4.422
    },
    {
      "time": "2026-05-20 12:54",
      "value_mllw": 4.307
    },
    {
      "time": "2026-05-20 13:00",
      "value_mllw": 4.176
    },
    {
      "time": "2026-05-20 13:06",
      "value_mllw": 4.048
    },
    {
      "time": "2026-05-20 13:12",
      "value_mllw": 3.946
    },
    {
      "time": "2026-05-20 13:18",
      "value_mllw": 3.805
    },
    {
      "time": "2026-05-20 13:24",
      "value_mllw": 3.67
    },
    {
      "time": "2026-05-20 13:30",
      "value_mllw": 3.536
    },
    {
      "time": "2026-05-20 13:36",
      "value_mllw": 3.418
    },
    {
      "time": "2026-05-20 13:42",
      "value_mllw": 3.27
    },
    {
      "time": "2026-05-20 13:48",
      "value_mllw": 3.139
    },
    {
      "time": "2026-05-20 13:54",
      "value_mllw": 3.014
    },
    {
      "time": "2026-05-20 14:00",
      "value_mllw": 2.896
    },
    {
      "time": "2026-05-20 14:06",
      "value_mllw": 2.752
    },
    {
      "time": "2026-05-20 14:12",
      "value_mllw": 2.65
    },
    {
      "time": "2026-05-20 14:18",
      "value_mllw": 2.535
    },
    {
      "time": "2026-05-20 14:24",
      "value_mllw": 2.427
    },
    {
      "time": "2026-05-20 14:30",
      "value_mllw": 2.292
    },
    {
      "time": "2026-05-20 14:36",
      "value_mllw": 2.214
    },
    {
      "time": "2026-05-20 14:42",
      "value_mllw": 2.099
    },
    {
      "time": "2026-05-20 14:48",
      "value_mllw": 1.987
    },
    {
      "time": "2026-05-20 14:54",
      "value_mllw": 1.882
    },
    {
      "time": "2026-05-20 15:00",
      "value_mllw": 1.787
    },
    {
      "time": "2026-05-20 15:06",
      "value_mllw": 1.692
    },
    {
      "time": "2026-05-20 15:12",
      "value_mllw": 1.59
    },
    {
      "time": "2026-05-20 15:18",
      "value_mllw": 1.489
    },
    {
      "time": "2026-05-20 15:24",
      "value_mllw": 1.403
    },
    {
      "time": "2026-05-20 15:30",
      "value_mllw": 1.321
    },
    {
      "time": "2026-05-20 15:36",
      "value_mllw": 1.226
    },
    {
      "time": "2026-05-20 15:42",
      "value_mllw": 1.16
    },
    {
      "time": "2026-05-20 15:48",
      "value_mllw": 1.075
    },
    {
      "time": "2026-05-20 15:54",
      "value_mllw": 1.0
    },
    {
      "time": "2026-05-20 16:00",
      "value_mllw": 0.924
    },
    {
      "time": "2026-05-20 16:06",
      "value_mllw": 0.849
    },
    {
      "time": "2026-05-20 16:12",
      "value_mllw": 0.806
    },
    {
      "time": "2026-05-20 16:18",
      "value_mllw": 0.721
    },
    {
      "time": "2026-05-20 16:24",
      "value_mllw": 0.665
    },
    {
      "time": "2026-05-20 16:30",
      "value_mllw": 0.586
    },
    {
      "time": "2026-05-20 16:36",
      "value_mllw": 0.527
    },
    {
      "time": "2026-05-20 16:42",
      "value_mllw": 0.481
    },
    {
      "time": "2026-05-20 16:48",
      "value_mllw": 0.403
    },
    {
      "time": "2026-05-20 16:54",
      "value_mllw": 0.344
    },
    {
      "time": "2026-05-20 17:00",
      "value_mllw": 0.291
    },
    {
      "time": "2026-05-20 17:06",
      "value_mllw": 0.258
    },
    {
      "time": "2026-05-20 17:12",
      "value_mllw": 0.209
    },
    {
      "time": "2026-05-20 17:18",
      "value_mllw": 0.196
    },
    {
      "time": "2026-05-20 17:24",
      "value_mllw": 0.166
    },
    {
      "time": "2026-05-20 17:30",
      "value_mllw": 0.157
    },
    {
      "time": "2026-05-20 17:36",
      "value_mllw": 0.15
    },
    {
      "time": "2026-05-20 17:42",
      "value_mllw": 0.173
    }
  ],
  "confidence_level": "low",
  "confidence_reason": "observed surge has swung 0.94 ft in the past 6 h \u2014 persistence assumption is unreliable",
  "confidence_uncertainty_ft": 0.5,
  "confidence_regime_band": [
    "dry",
    "street"
  ],
  "plain_language_summary": "Next 24 h: 11:57 PM tonight \u2014 dry; 12:45 PM tomorrow afternoon \u2014 dry; 12:58 AM Fri May 22 morning \u2014 dry; 1:44 PM Fri May 22 afternoon \u2014 dry; 1:55 AM Sat May 23 morning \u2014 dry; 2:39 PM Sat May 23 afternoon \u2014 dry.",
  "peak_percentile": {
    "p25_mllw": 5.13475,
    "p50_mllw": 5.55,
    "p75_mllw": 6.05425,
    "p90_mllw": 6.479,
    "p95_mllw": 6.7662999999999975,
    "p99_mllw": 7.335,
    "max_mllw": 7.739,
    "label": "above median",
    "window": "1996-2025 (30 yrs)"
  },
  "accuracy_summary": {
    "n_scored_total": 2,
    "n_scored_recent": 2,
    "mean_error_ft": 0.1324999999999994,
    "mean_abs_error_ft": 0.3064999999999998,
    "max_abs_error_ft": 0.43899999999999917,
    "recent_window": 30
  }
}